{
    "version": 2,
    "objs": [
        {
            "type": "parallel",
            "p1": {
                "type": 1,
                "x": 505,
                "y": 313,
                "exist": true
            },
            "p2": {
                "type": 1,
                "x": 405,
                "y": 313,
                "exist": true
            },
            "p": 0.5
        },
        {
            "type": "refractor",
            "path": [
                {
                    "x": 360,
                    "y": 500,
                    "arc": false
                },
                {
                    "x": 540,
                    "y": 680,
                    "arc": false
                },
                {
                    "x": 720,
                    "y": 500,
                    "arc": false
                }
            ],
            "notDone": false,
            "p": 2.03
        },
        {
            "type": "refractor",
            "path": [
                {
                    "x": 100,
                    "y": 500,
                    "arc": false
                },
                {
                    "x": 100,
                    "y": 660,
                    "arc": false
                },
                {
                    "x": 260,
                    "y": 500,
                    "arc": false
                }
            ],
            "notDone": false,
            "p": 1.99
        },
        {
            "type": "parallel",
            "p1": {
                "type": 1,
                "x": 220,
                "y": 300,
                "exist": true
            },
            "p2": {
                "type": 1,
                "x": 140,
                "y": 300,
                "exist": true
            },
            "p": 0.5
        },
        {
            "type": "refractor",
            "path": [
                {
                    "x": 140,
                    "y": 800,
                    "arc": false
                },
                {
                    "x": 40,
                    "y": 880,
                    "arc": false
                },
                {
                    "x": 320,
                    "y": 880,
                    "arc": false
                },
                {
                    "x": 220,
                    "y": 800,
                    "arc": false
                }
            ],
            "notDone": false,
            "p": 1.99
        },
        {
            "type": "parallel",
            "p1": {
                "type": 1,
                "x": -20,
                "y": 800,
                "exist": true
            },
            "p2": {
                "type": 1,
                "x": -20,
                "y": 860,
                "exist": true
            },
            "p": 0.5
        },
        {
            "type": "refractor",
            "path": [
                {
                    "x": 820,
                    "y": 700,
                    "arc": false
                },
                {
                    "x": 940,
                    "y": 580,
                    "arc": false
                },
                {
                    "x": 940,
                    "y": 400,
                    "arc": false
                },
                {
                    "x": 820,
                    "y": 520,
                    "arc": false
                }
            ],
            "notDone": false,
            "p": 1.9
        },
        {
            "type": "parallel",
            "p1": {
                "type": 1,
                "x": 760,
                "y": 600,
                "exist": true
            },
            "p2": {
                "type": 1,
                "x": 760,
                "y": 680,
                "exist": true
            },
            "p": 0.5
        },
        {
            "type": "text",
            "x": 766.5999999999998,
            "y": 455.37777777777796,
            "p": "菱形"
        },
        {
            "type": "text",
            "x": 125.93333333333354,
            "y": 683.7111111111112,
            "p": "直角"
        },
        {
            "type": "text",
            "x": 515.0716387039214,
            "y": 465.99589160387313,
            "p": "波罗"
        },
        {
            "type": "text",
            "x": 152.9333333333335,
            "y": 914.7111111111111,
            "p": "杜福"
        },
        {
            "type": "refractor",
            "path": [
                {
                    "x": 440.0493827160492,
                    "y": 880.9382716049383,
                    "arc": false
                },
                {
                    "x": 559.4719232606673,
                    "y": 880.382448432791,
                    "arc": false
                },
                {
                    "x": 602.2719232606672,
                    "y": 784.582448432791,
                    "arc": false
                },
                {
                    "x": 534.4219478165446,
                    "y": 724.9890531170365,
                    "arc": false
                },
                {
                    "x": 439.4432521495561,
                    "y": 761.5664484327909,
                    "arc": false
                }
            ],
            "notDone": false,
            "p": 1.5
        },
        {
            "type": "mirror",
            "p1": {
                "type": 1,
                "x": 560,
                "y": 880,
                "exist": true
            },
            "p2": {
                "type": 1,
                "x": 602.839702562603,
                "y": 782.5683516656995,
                "exist": true
            }
        },
        {
            "type": "mirror",
            "p1": {
                "type": 1,
                "x": 439.01234567901224,
                "y": 760.9876543209878,
                "exist": true
            },
            "p2": {
                "type": 1,
                "x": 535.776754841219,
                "y": 723.6342460923621,
                "exist": true
            }
        },
        {
            "type": "text",
            "x": 534.9816224388505,
            "y": 911.7172702972307,
            "p": "五面"
        }
    ],
    "mode": "light",
    "rayDensity_light": 0.1,
    "rayDensity_images": 1,
    "observer": null,
    "origin": {
        "x": 47.733489479072496,
        "y": -126.17932616398706
    },
    "scale": 1.1438396227480496
}