{
  "version": 2,
  "objs": [
    {
      "type": "ruler",
      "p1": {
        "type": 1,
        "x": 240,
        "y": 1660,
        "exist": true
      },
      "p2": {
        "type": 1,
        "x": 240,
        "y": 1060,
        "exist": true
      }
    },
    {
      "type": "text",
      "x": 1157.489153683247,
      "y": 1152.9975274295023,
      "p": "Powietrze (bez efektu mirażu dolnego)"
    },
    {
      "type": "lens",
      "p1": {
        "type": 1,
        "x": 1760,
        "y": 1360,
        "exist": true
      },
      "p2": {
        "type": 1,
        "x": 1760,
        "y": 1640,
        "exist": true
      },
      "p": 180
    },
    {
      "type": "ruler",
      "p1": {
        "type": 1,
        "x": 240,
        "y": 1000,
        "exist": true
      },
      "p2": {
        "type": 1,
        "x": 240,
        "y": 400,
        "exist": true
      }
    },
    {
      "type": "blackline",
      "p1": {
        "type": 1,
        "x": 260,
        "y": 1000,
        "exist": true
      },
      "p2": {
        "type": 1,
        "x": 2180,
        "y": 1000,
        "exist": true
      }
    },
    {
      "type": "lens",
      "p1": {
        "type": 1,
        "x": 1760,
        "y": 700,
        "exist": true
      },
      "p2": {
        "type": 1,
        "x": 1760,
        "y": 980,
        "exist": true
      },
      "p": "180"
    },
    {
      "type": "led",
      "p1": {
        "type": 1,
        "x": 320,
        "y": 1060,
        "exist": true
      },
      "p2": {
        "type": 1,
        "x": 791.9008264462811,
        "y": 1206.1157024793388,
        "exist": true
      },
      "p": "15",
      "symmetric": true,
      "brightness": 1
    },
    {
      "type": "text",
      "x": 1157.489153683247,
      "y": 552.9975274295023,
      "p": "Powietrze (z efektem mirażu dolnego)"
    },
    {
      "type": "text",
      "x": 1142.1637886361382,
      "y": 989.0955793479338,
      "p": "Grunt"
    },
    {
      "type": "text",
      "x": 372.29176768061257,
      "y": 415.70184882729745,
      "p": "Promienie emitowane/odbijane\nprzez obiekt"
    },
    {
      "type": "text",
      "x": 1630.390890452898,
      "y": 659.330960553045,
      "p": "Oko obserwatora (nie w skali)"
    },
    {
      "type": "text",
      "x": 1754.58686505484,
      "y": 690.9495449479587,
      "p": "↓"
    },
    {
      "type": "grin_refractor",
      "path": [
        {
          "x": 260,
          "y": 380,
          "arc": false
        },
        {
          "x": 260,
          "y": 1000,
          "arc": false
        },
        {
          "x": 2180,
          "y": 1000,
          "arc": false
        },
        {
          "x": 2180,
          "y": 380,
          "arc": false
        }
      ],
      "notDone": false,
      "origin": {
        "type": 1,
        "x": 260,
        "y": 1000,
        "exist": true
      },
      "p": "sqrt(1 + (y / 600) ^ 2)",
      "p_tex": "\\sqrt{1+\\left(\\frac{y}{600}\\right)^2}",
      "p_der_x": "0",
      "p_der_x_tex": "0",
      "p_der_y": "y / 3.6e+5 / sqrt(y ^ 2 / 3.6e+5 + 1)",
      "p_der_y_tex": "\\frac{\\frac{ y}{3.6\\cdot10^{5}}}{\\sqrt{\\frac{{ y}^{2}}{3.6\\cdot10^{5}}+1}}",
      "step_size": 1,
      "eps": 0.001
    },
    {
      "type": "led",
      "p1": {
        "type": 1,
        "x": 320,
        "y": 400,
        "exist": true
      },
      "p2": {
        "type": 1,
        "x": 440,
        "y": 520,
        "exist": true
      },
      "p": 15,
      "symmetric": true,
      "brightness": 1
    },
    {
      "type": "blackline",
      "p1": {
        "type": 1,
        "x": 260,
        "y": 380,
        "exist": true
      },
      "p2": {
        "type": 1,
        "x": 260,
        "y": 1000,
        "exist": true
      }
    },
    {
      "type": "blackline",
      "p1": {
        "type": 1,
        "x": 260,
        "y": 380,
        "exist": true
      },
      "p2": {
        "type": 1,
        "x": 2180,
        "y": 380,
        "exist": true
      }
    },
    {
      "type": "blackline",
      "p1": {
        "type": 1,
        "x": 2180,
        "y": 380,
        "exist": true
      },
      "p2": {
        "type": 1,
        "x": 2180,
        "y": 1000,
        "exist": true
      }
    },
    {
      "type": "blackline",
      "p1": {
        "type": 1,
        "x": 260,
        "y": 1660,
        "exist": true
      },
      "p2": {
        "type": 1,
        "x": 2180,
        "y": 1660,
        "exist": true
      }
    },
    {
      "type": "blackline",
      "p1": {
        "type": 1,
        "x": 260,
        "y": 1040,
        "exist": true
      },
      "p2": {
        "type": 1,
        "x": 260,
        "y": 1660,
        "exist": true
      }
    },
    {
      "type": "blackline",
      "p1": {
        "type": 1,
        "x": 260,
        "y": 1040,
        "exist": true
      },
      "p2": {
        "type": 1,
        "x": 2180,
        "y": 1040,
        "exist": true
      }
    },
    {
      "type": "blackline",
      "p1": {
        "type": 1,
        "x": 2180,
        "y": 1040,
        "exist": true
      },
      "p2": {
        "type": 1,
        "x": 2180,
        "y": 1660,
        "exist": true
      }
    },
    {
      "type": "text",
      "x": 260,
      "y": 360,
      "p": "Ostrzeżenie: sekwencja pojawiania się światła nie reprezentuje rzeczywistej prędkości światła - znaczenie ma tylko obraz końcowy.",
      "fontSize": "37",
      "fontName": "Serif",
      "fontStyle": "Normal",
      "fontAlignment": "left",
      "fontSmallCaps": false,
      "fontAngle": 0
    },
    {
      "type": "ruler",
      "p1": {
        "type": 1,
        "x": 2017,
        "y": 840,
        "exist": true
      },
      "p2": {
        "type": 1,
        "x": 2017,
        "y": 740,
        "exist": true
      }
    },
    {
      "type": "ruler",
      "p1": {
        "type": 1,
        "x": 1965,
        "y": 1500,
        "exist": true
      },
      "p2": {
        "type": 1,
        "x": 1965,
        "y": 1600,
        "exist": true
      }
    }
  ],
  "mode": "light",
  "rayDensity_light": 1.4861665211342676,
  "rayDensity_images": 1,
  "observer": null,
  "origin": {
    "x": 195.8999999999998,
    "y": -97.70000000000007
  },
  "scale": 0.6050000000000001,
  "colorMode": false,
  "symbolicGrin": false
}